flask_audit_logger/__init__.py
flask_audit_logger/audit_logger.py
flask_audit_logger/alembic_hooks/__init__.py
flask_audit_logger/alembic_hooks/setup_functions_and_triggers.py
flask_audit_logger/alembic_hooks/setup_schema.py
flask_audit_logger/templates/audit_trigger_delete.sql
flask_audit_logger/templates/audit_trigger_insert.sql
flask_audit_logger/templates/audit_trigger_update.sql
flask_audit_logger/templates/create_activity.sql
flask_audit_logger/templates/create_schema.sql
flask_audit_logger/templates/drop_schema.sql
flask_audit_logger/templates/get_setting.sql
flask_audit_logger/templates/jsonb_subtract.sql
flask_audit_logger-2.0.0.dist-info/METADATA
flask_audit_logger-2.0.0.dist-info/WHEEL
flask_audit_logger-2.0.0.dist-info/licenses/LICENSE
flask_audit_logger-2.0.0.dist-info/RECORD
