Metadata-Version: 2.4
Name: flask-audit-logger
Version: 2.0.0
Summary: Audit logs using Flask-SQLAlchemy and PostgreSQL.
Project-URL: Homepage, https://github.com/gmassman/flask-audit-logger
Author-email: Garrett Massman <gmassman20@gmail.com>
License-Expression: BSD-2-Clause
License-File: LICENSE
Classifier: Environment :: Web Environment
Classifier: Intended Audience :: Developers
Classifier: License :: OSI Approved :: BSD License
Classifier: Operating System :: OS Independent
Classifier: Programming Language :: Python
Classifier: Programming Language :: Python :: 3
Classifier: Programming Language :: Python :: 3.10
Classifier: Programming Language :: Python :: 3.11
Classifier: Programming Language :: Python :: 3.12
Classifier: Programming Language :: Python :: 3.13
Classifier: Topic :: Internet :: WWW/HTTP :: Dynamic Content
Classifier: Topic :: Software Development :: Libraries :: Python Modules
Requires-Python: >=3.10
Requires-Dist: alembic>=1.13
Requires-Dist: flask-sqlalchemy>=3.0
Requires-Dist: flask>=2.3
Requires-Dist: sqlalchemy>=1.4
